openboost/__init__.py
openboost/_array.py
openboost/_boosting.py
openboost/_histogram.py
openboost/_kernels.py
openboost/_split.py
openboost/_tree.py
openboost-0.1.0.dist-info/METADATA
openboost-0.1.0.dist-info/WHEEL
openboost-0.1.0.dist-info/licenses/LICENSE
openboost-0.1.0.dist-info/RECORD
