Metadata-Version: 2.4
Name: openboost
Version: 0.1.0
Summary: GPU-accelerated gradient boosting, written in Python
Project-URL: Homepage, https://github.com/jxucoder/openboost
Project-URL: Repository, https://github.com/jxucoder/openboost
Author: J. Xu
License-Expression: Apache-2.0
License-File: LICENSE
Keywords: cuda,gbdt,gpu,gradient-boosting,machine-learning
Classifier: Development Status :: 2 - Pre-Alpha
Classifier: Intended Audience :: Science/Research
Classifier: License :: OSI Approved :: Apache Software License
Classifier: Programming Language :: Python :: 3
Classifier: Programming Language :: Python :: 3.10
Classifier: Programming Language :: Python :: 3.11
Classifier: Programming Language :: Python :: 3.12
Classifier: Topic :: Scientific/Engineering :: Artificial Intelligence
Requires-Python: >=3.10
Requires-Dist: numba>=0.60
Requires-Dist: numpy>=1.24
Provides-Extra: bench
Requires-Dist: modal>=1.0; extra == 'bench'
Requires-Dist: scikit-learn>=1.0; extra == 'bench'
Requires-Dist: xgboost>=2.0; extra == 'bench'
Provides-Extra: cuda
Requires-Dist: numba-cuda>=0.23; extra == 'cuda'
Provides-Extra: dev
Requires-Dist: modal>=1.0; extra == 'dev'
Requires-Dist: pytest>=7.0; extra == 'dev'
Requires-Dist: scikit-learn>=1.0; extra == 'dev'
Requires-Dist: xgboost>=2.0; extra == 'dev'
Provides-Extra: test
Requires-Dist: pytest>=7.0; extra == 'test'
